decentgradients
